blockchain/__init.py__
blockchain/__init__.py
blockchain/admin/__init__.py
blockchain/admin/commands.py
blockchain/admin_v1/__init__.py
blockchain/admin_v1/commands.py
blockchain/artifacts/__init__.py
blockchain/artifacts/src/__init__.py
blockchain/artifacts/src/chaincodes/__init__.py
blockchain/artifacts/src/chaincodes/abstore/__init__.py
blockchain/artifacts/src/chaincodes/abstore/go/__init__.py
blockchain/artifacts/src/chaincodes/abstore/go/abstore.go
blockchain/artifacts/src/chaincodes/abstore/go/go.mod
blockchain/artifacts/src/chaincodes/abstore/go/go.sum
blockchain/artifacts/src/chaincodes/fabcar/__init__.py
blockchain/artifacts/src/chaincodes/fabcar/fabcar.go
blockchain/artifacts/src/chaincodes/fabcar/go.mod
blockchain/artifacts/src/chaincodes/fabcar/go.sum
blockchain/bootstrap_network/__init__.py
blockchain/bootstrap_network/commands.py
blockchain/channel_artifact/__init__.py
blockchain/channel_artifact/commands.py
blockchain/copyscripts/__init__.py
blockchain/copyscripts/commands.py
blockchain/create_org/__init__.py
blockchain/create_org/commands.py
blockchain/delete_network/__init__.py
blockchain/delete_network/commands.py
blockchain/enroll_orderers/__init__.py
blockchain/enroll_orderers/commands.py
blockchain/enroll_peers/__init__.py
blockchain/enroll_peers/commands.py
blockchain/explorer/__init__.py
blockchain/explorer/commands.py
blockchain/explorer/config.json
blockchain/external_chaincode/__init__.py
blockchain/external_chaincode/commands.py
blockchain/gen_artifact/__init__.py
blockchain/gen_artifact/commands.py
blockchain/generate_ccp/__init__.py
blockchain/generate_ccp/commands.py
blockchain/grafana/__init__.py
blockchain/grafana/commands.py
blockchain/ica/__init__.py
blockchain/ica/commands.py
blockchain/kafka/__init__.py
blockchain/kafka/commands.py
blockchain/orderer/__init__.py
blockchain/orderer/commands.py
blockchain/peer/__init__.py
blockchain/peer/commands.py
blockchain/prometheus/__init__.py
blockchain/prometheus/commands.py
akc_mamba-2.1.1.dist-info/METADATA
akc_mamba-2.1.1.dist-info/WHEEL
akc_mamba-2.1.1.dist-info/entry_points.txt
akc_mamba-2.1.1.dist-info/top_level.txt
akc_mamba-2.1.1.dist-info/RECORD
