Metadata-Version: 2.1
Name: akc-mamba
Version: 2.1.1
Summary: A production ready, complete experience in deploying a Hyperledger Fabric
Home-page: https://github.com/Akachain/akc-mamba
Author: akaChain
Author-email: admin@akachain.io
License: UNKNOWN
Keywords: mamba akc-mamba hyperledger fabric blockchain network
Platform: UNKNOWN
Classifier: Programming Language :: Python :: 3
Classifier: License :: OSI Approved :: MIT License
Classifier: Operating System :: OS Independent
Requires-Dist: Click (==7.0)
Requires-Dist: kubernetes (==10.0.1)
Requires-Dist: six (==1.13.0)
Requires-Dist: python-dotenv (==0.15.0)
Requires-Dist: gitdb2 (==2.0.6)
Requires-Dist: GitPython (==3.0.5)
